pylmm3/__init__.py
pylmm3/input.py
pylmm3/lmm.py
pylmm3/misc.py
pylmm3/scripts/__init__.py
pylmm3/scripts/example.py
pylmm3/scripts/pylmmGWAS.py
pylmm3/scripts/pylmmKinship.py
pylmm3-0.1.0.dist-info/entry_points.txt
pylmm3-0.1.0.dist-info/METADATA
pylmm3-0.1.0.dist-info/WHEEL
pylmm3-0.1.0.dist-info/RECORD
