Metadata-Version: 2.1
Name: pylmm3
Version: 0.1.0
Summary: Python 3 implementation of Pylmm
Home-page: https://bitbucket.org/jacksonlaboratory/pylmm3/src/master
License: AGPL-3.0-or-later
Author: Your Name
Author-email: you@example.com
Requires-Python: >=3.9,<4.0
Classifier: License :: OSI Approved :: GNU Affero General Public License v3 or later (AGPLv3+)
Classifier: Programming Language :: Python :: 3
Classifier: Programming Language :: Python :: 3.9
Classifier: Programming Language :: Python :: 3.10
Classifier: Programming Language :: Python :: 3.11
Classifier: Programming Language :: Python :: 3.12
Requires-Dist: numpy (>=1.21,<2.0)
Requires-Dist: scipy (>=1.7,<2.0)
Project-URL: Repository, https://bitbucket.org/jacksonlaboratory/pylmm3/src/master
